MANIFEST.in
README.md
RELEASE-VERSION
setup.cfg
setup.py
version.py
src/avoin/__init__.py
src/avoin/core.py
src/avoin/utils.py
src/avoin.egg-info/PKG-INFO
src/avoin.egg-info/SOURCES.txt
src/avoin.egg-info/dependency_links.txt
src/avoin.egg-info/entry_points.txt
src/avoin.egg-info/requires.txt
src/avoin.egg-info/top_level.txt
src/avoin/data/__init__.py
src/avoin/data/utils.py
src/avoin/scraper/__init__.py
src/avoin/scraper/scraper.py