Metadata-Version: 1.1
Name: avoin
Version: 0.0.9.dev-20121012
Summary: Misc python tools
Home-page: https://github.com/ypcs/avoin
Author: Ville Korhonen
Author-email: ville@xd.fi
License: GPLv3
Platform: UNKNOWN
Classifier: Development Status :: 3 - Alpha
Classifier: Environment :: Console
Classifier: Intended Audience :: End Users/Desktop
Classifier: Intended Audience :: Developers
Classifier: Operating System :: MacOS :: MacOS X
Classifier: Operating System :: Microsoft :: Windows
Classifier: Operating System :: POSIX
Classifier: Programming Language :: Python
Classifier: Topic :: Utilities
Classifier: License :: OSI Approved :: GNU General Public License v3 (GPLv3)
